nbplot/__init__.py
nbplot/__main__.py
nbplot/delim.py
nbplot/nbplot-user-config.ipynb
nbplot/nbplot.py
nbplot/utils.py
nbplot/templates/nbplot-daltonize.ipynb
nbplot/templates/nbplot-daltonlens.ipynb
nbplot/templates/nbplot-empty.ipynb
nbplot/templates/nbplot-imshow.ipynb
nbplot/templates/nbplot-numpy.ipynb
nbplot/templates/nbplot-pandas.ipynb
nbplot-0.4.dist-info/METADATA
nbplot-0.4.dist-info/WHEEL
nbplot-0.4.dist-info/entry_points.txt
nbplot-0.4.dist-info/licenses/LICENSE
nbplot-0.4.dist-info/RECORD
