Metadata-Version: 2.4
Name: nbplot
Version: 0.4
Summary: Command-line utility to quickly plot files in a Jupyter notebook
Project-URL: Homepage, https://github.com/nburrus/nbplot
Project-URL: Bug Tracker, https://github.com/nburrus/nbplot/issues
Author-email: Nicolas Burrus <nicolas@burrus.name>
License: MIT
License-File: LICENSE
Classifier: License :: OSI Approved :: MIT License
Classifier: Operating System :: OS Independent
Classifier: Programming Language :: Python :: 3
Requires-Python: >=3.8
Requires-Dist: ipympl
Requires-Dist: matplotlib
Requires-Dist: mplcursors
Requires-Dist: nbformat>=5.1
Requires-Dist: notebook>=7.0.0
Requires-Dist: numpy
Requires-Dist: traitlets
